LICENSE
great_scott/__init__.py
great_scott/__main__.py
great_scott/migrations.py
great_scott/setup.py
great_scott-0.1.1.dist-info/LICENSE
great_scott-0.1.1.dist-info/METADATA
great_scott-0.1.1.dist-info/WHEEL
great_scott-0.1.1.dist-info/entry_points.txt
great_scott-0.1.1.dist-info/RECORD
