Metadata-Version: 2.1
Name: great-scott
Version: 0.1.1
Summary: Automatically reverses Django migrations when changing git branches
Home-page: https://github.com/goreckim/great-scott
License: MIT
Keywords: Django,migrations,git
Author: Marcin Górecki
Author-email: marcin.gorecki@hey.com
Maintainer: Marcin Górecki
Maintainer-email: marcin.gorecki@hey.com
Requires-Python: >=3.8,<4.0
Classifier: Environment :: Console
Classifier: Framework :: Django
Classifier: Intended Audience :: Developers
Classifier: License :: OSI Approved :: MIT License
Classifier: Operating System :: OS Independent
Classifier: Programming Language :: Python :: 3
Classifier: Programming Language :: Python :: 3.8
Classifier: Programming Language :: Python :: 3.9
Classifier: Programming Language :: Python :: 3.10
Classifier: Programming Language :: Python :: 3.11
Classifier: Topic :: Software Development :: Build Tools
Classifier: Topic :: Software Development :: Libraries :: Python Modules
Classifier: Topic :: Software Development :: Version Control :: Git
Classifier: Topic :: Utilities
Project-URL: Repository, https://github.com/goreckim/great-scott
